common/Descriptor.py
common/Metaclass.py
common/__init__.py
common/decos.py
common/errors.py
common/logs_decorator.py
common/utils.py
common/variables.py
log_config/__init__.py
log_config/client_log_config.py
log_config/console_log_config.py
log_config/server_log_config.py
server/ServerStorage.py
server/__init__.py
server/add_user.py
server/config_window.py
server/core.py
server/main_window.py
server/remove_user.py
server/stst_window.py
unit_tests/__init__.py
unit_tests/test_client.py
unit_tests/test_server.py
unit_tests/test_utils.py
server_asyn_chat-0.1.dist-info/METADATA
server_asyn_chat-0.1.dist-info/WHEEL
server_asyn_chat-0.1.dist-info/top_level.txt
server_asyn_chat-0.1.dist-info/RECORD
