Metadata-Version: 2.1
Name: server-asyn-chat
Version: 0.1
Summary: Server packet
Author: Alex Ya
Author-email: ya_alexander@mail.ru
